.gitignore
CHANGES.txt
MANIFEST.in
README.rst
bootstrap.py
buildout.cfg
setup.py
docs/LICENSE.GPL
docs/LICENSE.txt
src/collective/__init__.py
src/collective.demositebadge.egg-info/PKG-INFO
src/collective.demositebadge.egg-info/SOURCES.txt
src/collective.demositebadge.egg-info/dependency_links.txt
src/collective.demositebadge.egg-info/entry_points.txt
src/collective.demositebadge.egg-info/namespace_packages.txt
src/collective.demositebadge.egg-info/not-zip-safe
src/collective.demositebadge.egg-info/requires.txt
src/collective.demositebadge.egg-info/top_level.txt
src/collective/demositebadge/__init__.py
src/collective/demositebadge/configure.zcml
src/collective/demositebadge/controlpanel.py
src/collective/demositebadge/interfaces.py
src/collective/demositebadge/testing.py
src/collective/demositebadge/views.py
src/collective/demositebadge/profiles/default/controlpanel.xml
src/collective/demositebadge/profiles/default/cssregistry.xml
src/collective/demositebadge/profiles/default/jsregistry.xml
src/collective/demositebadge/profiles/default/metadata.xml
src/collective/demositebadge/profiles/default/registry.xml
src/collective/demositebadge/resources/badge.js.pt
src/collective/demositebadge/resources/styles.css
src/collective/demositebadge/tests/__init__.py
src/collective/demositebadge/tests/test_installation.py
src/collective/demositebadge/tests/test_view.py