Metadata-Version: 1.0
Name: collective.demositebadge
Version: 1.0
Summary: Provides sticky badge for demo sites.
Home-page: http://github.com/martinschoel/collective.demositebadge
Author: Vitaliy Podoba
Author-email: vitaliy@martinschoel.com
License: GPL
Platform: UNKNOWN
Classifier: Environment :: Web Environment
Classifier: Framework :: Plone
Classifier: Operating System :: OS Independent
Classifier: Programming Language :: Python
Classifier: Programming Language :: Python :: 2.6
Classifier: Topic :: Software Development :: Libraries :: Python Modules
